easyhist/__init__.py
easyhist/hist.py
easyhist/plot.py
easyhist/utilities.py
easyhist-0.2.4.dist-info/METADATA
easyhist-0.2.4.dist-info/WHEEL
easyhist-0.2.4.dist-info/top_level.txt
easyhist-0.2.4.dist-info/RECORD
