Metadata-Version: 2.1
Name: easyhist
Version: 0.2.4
Home-page: https://github.com/pranphy/easyhist
Author: Prakash Gautam
Author-email: pranphy@gmail.com
Classifier: Programming Language :: Python :: 3
Classifier: Operating System :: OS Independent
